seiran/__init__.py
seiran/ff_bkm_import.py
seiran/onetab_bkm_import.py
seiran/seiran.py
seiran-1.6.0.data/data/seiran/docs/changelog.html
seiran-1.6.0.data/data/seiran/docs/genindex.html
seiran-1.6.0.data/data/seiran/docs/index.html
seiran-1.6.0.data/data/seiran/docs/modules.html
seiran-1.6.0.data/data/seiran/docs/objects.inv
seiran-1.6.0.data/data/seiran/docs/py-modindex.html
seiran-1.6.0.data/data/seiran/docs/quickstart.html
seiran-1.6.0.data/data/seiran/docs/search.html
seiran-1.6.0.data/data/seiran/docs/searchindex.js
seiran-1.6.0.data/data/seiran/docs/seiran.html
seiran-1.6.0.data/data/seiran/docs/_sources/changelog.rst.txt
seiran-1.6.0.data/data/seiran/docs/_sources/index.rst.txt
seiran-1.6.0.data/data/seiran/docs/_sources/modules.rst.txt
seiran-1.6.0.data/data/seiran/docs/_sources/quickstart.rst.txt
seiran-1.6.0.data/data/seiran/docs/_sources/seiran.rst.txt
seiran-1.6.0.data/data/seiran/docs/_static/doctools.js
seiran-1.6.0.data/data/seiran/docs/_static/documentation_options.js
seiran-1.6.0.data/data/seiran/docs/_static/jquery-3.5.1.js
seiran-1.6.0.data/data/seiran/docs/_static/jquery.js
seiran-1.6.0.data/data/seiran/docs/_static/language_data.js
seiran-1.6.0.data/data/seiran/docs/_static/pygments.css
seiran-1.6.0.data/data/seiran/docs/_static/pyramida.css
seiran-1.6.0.data/data/seiran/docs/_static/searchtools.js
seiran-1.6.0.data/data/seiran/docs/_static/seiran.svg
seiran-1.6.0.data/data/seiran/docs/_static/underscore-1.3.1.js
seiran-1.6.0.data/data/seiran/docs/_static/underscore.js
seiran-1.6.0.data/data/seiran/docsource/changelog.rst
seiran-1.6.0.data/data/seiran/docsource/conf.py
seiran-1.6.0.data/data/seiran/docsource/index.rst
seiran-1.6.0.data/data/seiran/docsource/modules.rst
seiran-1.6.0.data/data/seiran/docsource/quickstart.rst
seiran-1.6.0.data/data/seiran/docsource/seiran.rst
seiran-1.6.0.data/data/seiran/docsource/_static/seiran.svg
seiran-1.6.0.dist-info/AUTHORS
seiran-1.6.0.dist-info/LICENSE
seiran-1.6.0.dist-info/METADATA
seiran-1.6.0.dist-info/WHEEL
seiran-1.6.0.dist-info/entry_points.txt
seiran-1.6.0.dist-info/top_level.txt
seiran-1.6.0.dist-info/RECORD
