Metadata-Version: 2.1
Name: seiran
Version: 1.6.0
Summary: Local bookmarks manager
Home-page: https://www.twinkle-night.net/Code/seiran.html
Author: Garrick
Author-email: earthisthering@posteo.de
License: GPLv3+
Keywords: bookmarks
Platform: UNKNOWN
Classifier: Development Status :: 4 - Beta
Classifier: License :: OSI Approved :: GNU General Public License v3 or later (GPLv3+)
Classifier: Programming Language :: Python :: 3
Classifier: Intended Audience :: End Users/Desktop
Classifier: Topic :: Internet
Requires-Dist: appdirs
Provides-Extra: docs
Requires-Dist: sphinx (>=3.4.1) ; extra == 'docs'
Requires-Dist: numpydoc ; extra == 'docs'
